autodan/__init__.py
autodan/config.py
autodan/core.py
autodan/assets/autodan_initial_prompt.txt
autodan/assets/prompt_group.pth
autodan/data/advbench/harmful_behaviors.csv
masterkey/__init__.py
masterkey/config.py
masterkey/core.py
masterkey/main.py
masterkey/masterkey_zeroshot.py
llm_jailbreak-0.2.2.dist-info/METADATA
llm_jailbreak-0.2.2.dist-info/WHEEL
llm_jailbreak-0.2.2.dist-info/entry_points.txt
llm_jailbreak-0.2.2.dist-info/top_level.txt
llm_jailbreak-0.2.2.dist-info/RECORD
