Metadata-Version: 2.4
Name: llm_jailbreak
Version: 0.2.2
Summary: A jailbreak package which integration some open manners
Author: Jay Woden
Author-email: wodenjay@gmail.com
Classifier: Programming Language :: Python :: 3
Classifier: License :: OSI Approved :: MIT License
Classifier: Operating System :: OS Independent
Requires-Python: >=3.8
Requires-Dist: torch>=2.0.1
Requires-Dist: transformers>=4.28.0
Requires-Dist: numpy>=1.26.0
Requires-Dist: tqdm>=4.66.1
Provides-Extra: autodan
Requires-Dist: accelerate>=0.23.0; extra == "autodan"
Requires-Dist: fschat==0.2.20; extra == "autodan"
Requires-Dist: nltk>=3.8.1; extra == "autodan"
Requires-Dist: openai>=1.12.0; extra == "autodan"
Requires-Dist: sentencepiece>=0.1.99; extra == "autodan"
Requires-Dist: protobuf>=4.24.4; extra == "autodan"
Provides-Extra: masterkey
Requires-Dist: openai==1.34.0; extra == "masterkey"
Requires-Dist: retry==0.9.2; extra == "masterkey"
Requires-Dist: loguru==0.7.2; extra == "masterkey"
Requires-Dist: httpx==0.26.0; extra == "masterkey"
Provides-Extra: all
Requires-Dist: llm_jailbreak[autodan,masterkey]; extra == "all"
Requires-Dist: openai==1.34.0; extra == "all"
Dynamic: author
Dynamic: author-email
Dynamic: classifier
Dynamic: description
Dynamic: description-content-type
Dynamic: provides-extra
Dynamic: requires-dist
Dynamic: requires-python
Dynamic: summary
